avantpy/__init__.py
avantpy/__main__.py
avantpy/console.py
avantpy/converter.py
avantpy/dialects/__init__.py
avantpy/dialects/pyen.py
avantpy/dialects/pyes.py
avantpy/dialects/pyfr.py
avantpy/dialects/pyga.py
avantpy/dialects/pyupper.py
avantpy/exception_handling.py
avantpy/exceptions.py
avantpy/gui.py
avantpy/import_hook.py
avantpy/invocation.py
avantpy/locales/avantpy.pot
avantpy/locales/fr/LC_MESSAGES/avantpy.mo
avantpy/locales/fr/LC_MESSAGES/avantpy.po
avantpy/locales/ga/LC_MESSAGES/avantpy.mo
avantpy/locales/ga/LC_MESSAGES/avantpy.po
avantpy/make_pot.bat
avantpy/my_gettext.py
avantpy/session.py
avantpy/utils.py
avantpy/version.py
avantpy/wrappers/__init__.py
avantpy/wrappers/_index.ga.yaml
avantpy/wrappers/_translated.py
avantpy/wrappers/antam.yaml
avantpy_extended-0.1.2.dist-info/LICENSE
avantpy_extended-0.1.2.dist-info/WHEEL
avantpy_extended-0.1.2.dist-info/METADATA
avantpy_extended-0.1.2.dist-info/RECORD
