Metadata-Version: 2.1
Name: avantpy-extended
Version: 0.1.2
Summary: AvantPy with Extensions
License: MIT
Author: André Roberge
Author-email: andre.roberge@gmail.com
Requires-Python: >=3.9,<4.0
Classifier: License :: OSI Approved :: MIT License
Classifier: Programming Language :: Python :: 3
Classifier: Programming Language :: Python :: 3.10
Classifier: Programming Language :: Python :: 3.9
Requires-Dist: PyYAML (>=6.0,<7.0)
Requires-Dist: Unidecode (>=1.3.2,<2.0.0)
Requires-Dist: friendly-traceback (==0.0.10)
Requires-Dist: requests (>=2.26.0,<3.0.0)
Requires-Dist: unicode (>=2.8,<3.0)
Requires-Dist: xdg (>=5.1.1,<6.0.0)
